mssql_mcp/__init__.py
mssql_mcp/server.py
mssql_mcp-0.1.0.dist-info/METADATA
mssql_mcp-0.1.0.dist-info/WHEEL
mssql_mcp-0.1.0.dist-info/entry_points.txt
mssql_mcp-0.1.0.dist-info/licenses/LICENSE
mssql_mcp-0.1.0.dist-info/RECORD
