Metadata-Version: 2.4
Name: mssql_mcp
Version: 0.1.0
Summary: A Model Context Protocol (MCP) server that enables secure interaction with Microsoft SQL Server databases.
License-File: LICENSE
Requires-Python: >=3.11
Requires-Dist: python-tds>=1.16.1
